ZeroSeg_API/__init__.py
ZeroSeg_API/api.py
ZeroSeg_API-0.3.dist-info/LICENSE
ZeroSeg_API-0.3.dist-info/METADATA
ZeroSeg_API-0.3.dist-info/WHEEL
ZeroSeg_API-0.3.dist-info/top_level.txt
ZeroSeg_API-0.3.dist-info/RECORD
