Metadata-Version: 2.1
Name: ZeroSeg-API
Version: 0.3
Summary: REST API for ZeroSeg Improved library.
Home-page: https://github.com/samedamci/ZeroSeg_API
Author: samedamci
Author-email: samedamci@disroot.org
License: ISC
Project-URL: Issue tracker, https://github.com/samedamci/ZeroSeg_API/issues
Keywords: raspberry pi rpi led max7219 matrix seven segment zeroseg api
Platform: UNKNOWN
Classifier: Intended Audience :: Developers
Classifier: Programming Language :: Python :: 3
Classifier: Programming Language :: Python :: 3.5
Classifier: Programming Language :: Python :: 3.6
Classifier: Programming Language :: Python :: 3.7
Classifier: Programming Language :: Python :: 3.8
Classifier: Programming Language :: Python :: 3 :: Only
Classifier: Programming Language :: Python :: Implementation :: CPython
Classifier: Programming Language :: Python :: Implementation :: PyPy
Classifier: License :: OSI Approved :: ISC License (ISCL)
Classifier: Operating System :: POSIX :: Linux
Requires-Python: >=3.6
Requires-Dist: flask
Requires-Dist: ZeroSeg-Improved
